DIYables_Pico_Ultrasonic_Sensor/DIYables_Pico_Ultrasonic_Sensor.py
DIYables_Pico_Ultrasonic_Sensor/__init__.py
DIYables_Pico_Ultrasonic_Sensor-0.1.1.dist-info/LICENSE
DIYables_Pico_Ultrasonic_Sensor-0.1.1.dist-info/METADATA
DIYables_Pico_Ultrasonic_Sensor-0.1.1.dist-info/WHEEL
DIYables_Pico_Ultrasonic_Sensor-0.1.1.dist-info/top_level.txt
DIYables_Pico_Ultrasonic_Sensor-0.1.1.dist-info/RECORD
